ImpactLearning/__init__.py
ImpactLearning-1.8.dist-info/LICENSE
ImpactLearning-1.8.dist-info/METADATA
ImpactLearning-1.8.dist-info/WHEEL
ImpactLearning-1.8.dist-info/top_level.txt
ImpactLearning-1.8.dist-info/RECORD
