Metadata-Version: 2.1
Name: ImpactLearning
Version: 1.8
Summary: UNKNOWN
Home-page: https://github.com/Kowsher/Impact-Learning-
Author: Kowsher Ahmed, Avishek Das
Author-email: ahmedshuvo969@gmail.com, avishek.das.ayan@gmail.com
License: MIT
Platform: UNKNOWN
Classifier: Programming Language :: Python :: 3
Classifier: License :: OSI Approved :: MIT License
Classifier: Operating System :: OS Independent
Requires-Dist: h5py (==2.10.0)
Requires-Dist: tensorflow (==2.2.0)
Requires-Dist: numpy (==1.18.5)
